LICENSE
MANIFEST.in
README.md
requirements.txt
setup.py
./interpreter/__init__.py
./interpreter/__main__.py
./interpreter/cli.py
./interpreter/interpret.py
./interpreter/maghilchiIDE.py
./interpreter/internal/__init__.py
./interpreter/internal/exceptions.py
./interpreter/internal/interfaces.py
./interpreter/internal/interpreter.py
./interpreter/internal/lexer.py
./interpreter/internal/parsing.py
./interpreter/internal/token_.py
./interpreter/internal/tokenvalue.py
./interpreter/tokens_/__init__.py
./interpreter/tokens_/compiler.py
./interpreter/tokens_/tokens.py
./interpreter/util/__init__.py
./interpreter/util/path.py
./interpreter/util/pattern_matching.py
interpreter/py.typed
maghilchiplusplus.egg-info/PKG-INFO
maghilchiplusplus.egg-info/SOURCES.txt
maghilchiplusplus.egg-info/dependency_links.txt
maghilchiplusplus.egg-info/entry_points.txt
maghilchiplusplus.egg-info/not-zip-safe
maghilchiplusplus.egg-info/top_level.txt